odoo/addons/maintenance_equipment_meter/README.rst
odoo/addons/maintenance_equipment_meter/__init__.py
odoo/addons/maintenance_equipment_meter/__manifest__.py
odoo/addons/maintenance_equipment_meter/i18n/fr.po
odoo/addons/maintenance_equipment_meter/i18n/it.po
odoo/addons/maintenance_equipment_meter/i18n/maintenance_equipment_meter.pot
odoo/addons/maintenance_equipment_meter/models/__init__.py
odoo/addons/maintenance_equipment_meter/models/maintenance_equipment.py
odoo/addons/maintenance_equipment_meter/models/maintenance_equipment_meter.py
odoo/addons/maintenance_equipment_meter/models/maintenance_request.py
odoo/addons/maintenance_equipment_meter/readme/CONTRIBUTORS.md
odoo/addons/maintenance_equipment_meter/readme/DESCRIPTION.md
odoo/addons/maintenance_equipment_meter/security/ir.model.access.csv
odoo/addons/maintenance_equipment_meter/static/description/icon.png
odoo/addons/maintenance_equipment_meter/static/description/index.html
odoo/addons/maintenance_equipment_meter/tests/__init__.py
odoo/addons/maintenance_equipment_meter/tests/test_equipment_meter.py
odoo/addons/maintenance_equipment_meter/views/maintenance_equipment.xml
odoo/addons/maintenance_equipment_meter/views/maintenance_equipment_meter.xml
odoo/addons/maintenance_equipment_meter/views/maintenance_request.xml
odoo14_addon_maintenance_equipment_meter-14.0.1.0.1.dev5.dist-info/METADATA
odoo14_addon_maintenance_equipment_meter-14.0.1.0.1.dev5.dist-info/WHEEL
odoo14_addon_maintenance_equipment_meter-14.0.1.0.1.dev5.dist-info/top_level.txt
odoo14_addon_maintenance_equipment_meter-14.0.1.0.1.dev5.dist-info/RECORD
